docs/__init__.py
physiopy/__init__.py
physiopy/_version.py
physiopy-0.0.1b0.dist-info/LICENSE
physiopy-0.0.1b0.dist-info/METADATA
physiopy-0.0.1b0.dist-info/WHEEL
physiopy-0.0.1b0.dist-info/top_level.txt
physiopy-0.0.1b0.dist-info/RECORD
